complexdecimal/__init__.py
complexdecimal/constants.py
complexdecimal/errors.py
complexdecimal-1.0.3.dist-info/DESCRIPTION.rst
complexdecimal-1.0.3.dist-info/METADATA
complexdecimal-1.0.3.dist-info/RECORD
complexdecimal-1.0.3.dist-info/WHEEL
complexdecimal-1.0.3.dist-info/metadata.json
complexdecimal-1.0.3.dist-info/top_level.txt
