Metadata-Version: 2.0
Name: complexdecimal
Version: 1.0.3
Summary: Python Decimal support for complex Numbers
Home-page: https://github.com/Bowserinator/ComplexDecimal
Author: Bowserinator
Author-email: bowserinator@gmail.com
License: GNU
Platform: UNKNOWN
